Metadata-Version: 2.4
Name: hops-deltalake
Version: 1.1.2.post2
Classifier: License :: OSI Approved :: Apache Software License
Classifier: Programming Language :: Python :: 3.9
Classifier: Programming Language :: Python :: 3.10
Classifier: Programming Language :: Python :: 3.11
Classifier: Programming Language :: Python :: 3.12
Requires-Dist: arro3-core>=0.5.0
Requires-Dist: deprecated>=1.2.18
Requires-Dist: pandas ; extra == 'pandas'
Requires-Dist: pyarrow>=16 ; extra == 'pyarrow'
Provides-Extra: pandas
Provides-Extra: pyarrow
License-File: LICENSE.txt
Summary: A HopsFS compatible version of Delta Lake Python binding based on delta-rs
Keywords: deltalake,delta,datalake,pandas,arrow,hopsfs
Home-Page: https://github.com/logicalclocks/delta-rs
License-Expression: MIT
Requires-Python: >=3.9
Project-URL: documentation, https://delta-io.github.io/delta-rs/
Project-URL: repository, https://github.com/delta-io/delta-rs/tree/main/python/
